{
  "id": {
    "valgaar": "2021",
    "valgtype": "ST",
    "nivaa": "stemmekrets",
    "navn": "Uoppgitt krets",
    "nr": "0000"
  },
  "tidspunkt": {
    "rapportGenerert": "2023-05-11T14:50:25",
    "sisteStemmer": "2021-09-17T13:55:26"
  },
  "merknader": [],
  "antallsb": 258,
  "mandater": {
    "antall": 0,
    "endring": null
  },
  "stemmer": {
    "total": 15130,
    "fhs": 15103,
    "totalForkastede": 41,
    "fhsForkastede": 40
  },
  "stemmegiving": {
    "totalGodkjente": 46,
    "fhsGodkjente": 42,
    "totalForkastede": 44,
    "fhsForkastede": 18
  },
  "frammote": {
    "prosent": null,
    "endring": null,
    "prosentStemmegiving": 17.8
  },
  "opptalt": {
    "forelopigFhs": 100.0,
    "forelopigVts": 100.0,
    "forelopig": 100.0,
    "endelig": 100.0,
    "oppgjor": 100.0
  },
  "prognose": {
    "beregnet": false,
    "historiskTotalavvik": null
  },
  "partier": [
    {
      "id": {
        "partikategori": 1,
        "partikode": "A",
        "navn": "Arbeiderpartiet"
      },
      "stemmer": {
        "resultat": {
          "prosent": 30.40117,
          "endring": {
            "samme": null
          },
          "antall": {
            "total": 4562,
            "fhs": 4553
          }
        }
      }
    },
    {
      "id": {
        "partikategori": 1,
        "partikode": "SV",
        "navn": "SV - Sosialistisk Venstreparti"
      },
      "stemmer": {
        "resultat": {
          "prosent": 7.85019,
          "endring": {
            "samme": null
          },
          "antall": {
            "total": 1178,
            "fhs": 1174
          }
        }
      }
    },
    {
      "id": {
        "partikategori": 1,
        "partikode": "RØDT",
        "navn": "Rødt"
      },
      "stemmer": {
        "resultat": {
          "prosent": 4.17833,
          "endring": {
            "samme": null
          },
          "antall": {
            "total": 627,
            "fhs": 627
          }
        }
      }
    },
    {
      "id": {
        "partikategori": 1,
        "partikode": "SP",
        "navn": "Senterpartiet"
      },
      "stemmer": {
        "resultat": {
          "prosent": 6.13754,
          "endring": {
            "samme": null
          },
          "antall": {
            "total": 921,
            "fhs": 920
          }
        }
      }
    },
    {
      "id": {
        "partikategori": 1,
        "partikode": "KRF",
        "navn": "Kristelig Folkeparti"
      },
      "stemmer": {
        "resultat": {
          "prosent": 1.65934,
          "endring": {
            "samme": null
          },
          "antall": {
            "total": 249,
            "fhs": 247
          }
        }
      }
    },
    {
      "id": {
        "partikategori": 1,
        "partikode": "MDG",
        "navn": "Miljøpartiet De Grønne"
      },
      "stemmer": {
        "resultat": {
          "prosent": 4.41157,
          "endring": {
            "samme": null
          },
          "antall": {
            "total": 662,
            "fhs": 662
          }
        }
      }
    },
    {
      "id": {
        "partikategori": 1,
        "partikode": "V",
        "navn": "Venstre"
      },
      "stemmer": {
        "resultat": {
          "prosent": 4.81807,
          "endring": {
            "samme": null
          },
          "antall": {
            "total": 723,
            "fhs": 723
          }
        }
      }
    },
    {
      "id": {
        "partikategori": 1,
        "partikode": "H",
        "navn": "Høyre"
      },
      "stemmer": {
        "resultat": {
          "prosent": 25.79635,
          "endring": {
            "samme": null
          },
          "antall": {
            "total": 3871,
            "fhs": 3865
          }
        }
      }
    },
    {
      "id": {
        "partikategori": 1,
        "partikode": "FRP",
        "navn": "Fremskrittspartiet"
      },
      "stemmer": {
        "resultat": {
          "prosent": 11.01559,
          "endring": {
            "samme": null
          },
          "antall": {
            "total": 1653,
            "fhs": 1650
          }
        }
      }
    },
    {
      "id": {
        "partikategori": 2,
        "partikode": "AAN",
        "navn": "Alliansen - Alternativ for Norge"
      },
      "stemmer": {
        "resultat": {
          "prosent": 0.0733,
          "endring": {
            "samme": null
          },
          "antall": {
            "total": 11,
            "fhs": 11
          }
        }
      }
    },
    {
      "id": {
        "partikategori": 2,
        "partikode": "DEMN",
        "navn": "Demokratene"
      },
      "stemmer": {
        "resultat": {
          "prosent": 1.01959,
          "endring": {
            "samme": null
          },
          "antall": {
            "total": 153,
            "fhs": 153
          }
        }
      }
    },
    {
      "id": {
        "partikategori": 2,
        "partikode": "FNB",
        "navn": "Folkeaksjonen Nei til mer bompenger"
      },
      "stemmer": {
        "resultat": {
          "prosent": 0.3332,
          "endring": {
            "samme": null
          },
          "antall": {
            "total": 50,
            "fhs": 50
          }
        }
      }
    },
    {
      "id": {
        "partikategori": 2,
        "partikode": "HELSE",
        "navn": "Helsepartiet"
      },
      "stemmer": {
        "resultat": {
          "prosent": 0.36652,
          "endring": {
            "samme": null
          },
          "antall": {
            "total": 55,
            "fhs": 55
          }
        }
      }
    },
    {
      "id": {
        "partikategori": 2,
        "partikode": "INP",
        "navn": "Industri- og Næringspartiet"
      },
      "stemmer": {
        "resultat": {
          "prosent": 0.08663,
          "endring": {
            "samme": null
          },
          "antall": {
            "total": 13,
            "fhs": 13
          }
        }
      }
    },
    {
      "id": {
        "partikategori": 2,
        "partikode": "KRISTNE",
        "navn": "Partiet De Kristne"
      },
      "stemmer": {
        "resultat": {
          "prosent": 0.25323,
          "endring": {
            "samme": null
          },
          "antall": {
            "total": 38,
            "fhs": 38
          }
        }
      }
    },
    {
      "id": {
        "partikategori": 2,
        "partikode": "LIBS",
        "navn": "Liberalistene"
      },
      "stemmer": {
        "resultat": {
          "prosent": 0.1666,
          "endring": {
            "samme": null
          },
          "antall": {
            "total": 25,
            "fhs": 25
          }
        }
      }
    },
    {
      "id": {
        "partikategori": 2,
        "partikode": "PIR",
        "navn": "Piratpartiet"
      },
      "stemmer": {
        "resultat": {
          "prosent": 0.09996,
          "endring": {
            "samme": null
          },
          "antall": {
            "total": 15,
            "fhs": 15
          }
        }
      }
    },
    {
      "id": {
        "partikategori": 2,
        "partikode": "PP",
        "navn": "Pensjonistpartiet"
      },
      "stemmer": {
        "resultat": {
          "prosent": 0.98627,
          "endring": {
            "samme": null
          },
          "antall": {
            "total": 148,
            "fhs": 146
          }
        }
      }
    },
    {
      "id": {
        "partikategori": 2,
        "partikode": "PS",
        "navn": "Partiet Sentrum"
      },
      "stemmer": {
        "resultat": {
          "prosent": 0.29322,
          "endring": {
            "samme": null
          },
          "antall": {
            "total": 44,
            "fhs": 44
          }
        }
      }
    },
    {
      "id": {
        "partikategori": 3,
        "partikode": "BLANKE",
        "navn": "Blanke"
      },
      "stemmer": {
        "resultat": {
          "prosent": 0.82634,
          "endring": {
            "samme": null
          },
          "antall": {
            "total": 124,
            "fhs": 124
          }
        }
      }
    },
    {
      "id": {
        "partikategori": 3,
        "partikode": "GENE",
        "navn": "Generasjonspartiet"
      },
      "stemmer": {
        "resultat": {
          "prosent": 0.05331,
          "endring": {
            "samme": null
          },
          "antall": {
            "total": 8,
            "fhs": 8
          }
        }
      }
    },
    {
      "id": {
        "partikategori": 0,
        "partikode": "Andre",
        "navn": "Andre"
      },
      "stemmer": {
        "resultat": {
          "prosent": 3.73184,
          "endring": {
            "samme": null
          },
          "antall": {
            "total": 560,
            "fhs": 558
          }
        }
      }
    },
    {
      "id": {
        "partikategori": 0,
        "partikode": "Andre2",
        "navn": "Andre2"
      },
      "stemmer": {
        "resultat": {
          "prosent": 0.0,
          "endring": {
            "samme": null
          },
          "antall": {
            "total": 0,
            "fhs": 0
          }
        }
      }
    }
  ],
  "_links": {
    "related": [],
    "self": {
      "nr": "0000",
      "href": "/2021/st/02/3029/0000",
      "hrefNavn": "/2021/st/akershus/l%C3%B8renskog/uoppgitt+krets",
      "navn": "Uoppgitt krets",
      "forelopigFhs": 100.0,
      "forelopigVts": 100.0,
      "forelopig": 100.0,
      "endelig": 100.0,
      "oppgjor": 100.0
    },
    "up": {
      "nr": "3029",
      "href": "/2021/st/02/3029",
      "hrefNavn": "/2021/st/akershus/l%C3%B8renskog",
      "navn": "Lørenskog"
    }
  }
}