{
  "id": {
    "valgaar": "2025",
    "valgtype": "ST",
    "nivaa": "stemmekrets",
    "navn": "IKEA",
    "nr": "4013",
    "forhaandsstemmelokale": true
  },
  "tidspunkt": {
    "rapportGenerert": "2025-09-12T13:00:45",
    "sisteStemmer": "2025-09-12T13:00:31"
  },
  "merknader": [],
  "antallsb": 0,
  "mandater": {
    "antall": 0,
    "endring": null
  },
  "stemmer": {
    "total": 5703,
    "fhs": 5703,
    "totalForkastede": 0,
    "fhsForkastede": 0
  },
  "stemmegiving": {
    "totalGodkjente": 0,
    "fhsGodkjente": 0,
    "totalForkastede": 0,
    "fhsForkastede": 0
  },
  "frammote": {
    "prosent": null,
    "prosentAndelFhs": null
  },
  "opptellingsStatusKrets": {
    "type": "stemmekrets",
    "kretsStatus": "kontrollFerdig"
  },
  "partier": [
    {
      "id": {
        "partikategori": 1,
        "partikode": "A",
        "navn": "Arbeiderpartiet"
      },
      "stemmer": {
        "resultat": {
          "prosent": 27.71787,
          "endring": {
            "samme": null
          },
          "antall": {
            "total": 1568,
            "fhs": 1568
          }
        }
      }
    },
    {
      "id": {
        "partikategori": 1,
        "partikode": "SV",
        "navn": "SV - Sosialistisk Venstreparti"
      },
      "stemmer": {
        "resultat": {
          "prosent": 5.03801,
          "endring": {
            "samme": null
          },
          "antall": {
            "total": 285,
            "fhs": 285
          }
        }
      }
    },
    {
      "id": {
        "partikategori": 1,
        "partikode": "RØDT",
        "navn": "Rødt"
      },
      "stemmer": {
        "resultat": {
          "prosent": 3.83596,
          "endring": {
            "samme": null
          },
          "antall": {
            "total": 217,
            "fhs": 217
          }
        }
      }
    },
    {
      "id": {
        "partikategori": 1,
        "partikode": "SP",
        "navn": "Senterpartiet"
      },
      "stemmer": {
        "resultat": {
          "prosent": 2.20965,
          "endring": {
            "samme": null
          },
          "antall": {
            "total": 125,
            "fhs": 125
          }
        }
      }
    },
    {
      "id": {
        "partikategori": 1,
        "partikode": "KRF",
        "navn": "Kristelig Folkeparti"
      },
      "stemmer": {
        "resultat": {
          "prosent": 3.65918,
          "endring": {
            "samme": null
          },
          "antall": {
            "total": 207,
            "fhs": 207
          }
        }
      }
    },
    {
      "id": {
        "partikategori": 1,
        "partikode": "MDG",
        "navn": "Miljøpartiet De Grønne"
      },
      "stemmer": {
        "resultat": {
          "prosent": 3.62383,
          "endring": {
            "samme": null
          },
          "antall": {
            "total": 205,
            "fhs": 205
          }
        }
      }
    },
    {
      "id": {
        "partikategori": 1,
        "partikode": "V",
        "navn": "Venstre"
      },
      "stemmer": {
        "resultat": {
          "prosent": 3.0228,
          "endring": {
            "samme": null
          },
          "antall": {
            "total": 171,
            "fhs": 171
          }
        }
      }
    },
    {
      "id": {
        "partikategori": 1,
        "partikode": "H",
        "navn": "Høyre"
      },
      "stemmer": {
        "resultat": {
          "prosent": 18.27824,
          "endring": {
            "samme": null
          },
          "antall": {
            "total": 1034,
            "fhs": 1034
          }
        }
      }
    },
    {
      "id": {
        "partikategori": 1,
        "partikode": "FRP",
        "navn": "Fremskrittspartiet"
      },
      "stemmer": {
        "resultat": {
          "prosent": 28.91992,
          "endring": {
            "samme": null
          },
          "antall": {
            "total": 1636,
            "fhs": 1636
          }
        }
      }
    },
    {
      "id": {
        "partikategori": 2,
        "partikode": "DEMN",
        "navn": "Norgesdemokratene"
      },
      "stemmer": {
        "resultat": {
          "prosent": 0.47728,
          "endring": {
            "samme": null
          },
          "antall": {
            "total": 27,
            "fhs": 27
          }
        }
      }
    },
    {
      "id": {
        "partikategori": 2,
        "partikode": "DNI",
        "navn": "Partiet DNI"
      },
      "stemmer": {
        "resultat": {
          "prosent": 0.15909,
          "endring": {
            "samme": null
          },
          "antall": {
            "total": 9,
            "fhs": 9
          }
        }
      }
    },
    {
      "id": {
        "partikategori": 2,
        "partikode": "FRED",
        "navn": "Fred og Rettferdighet (FOR)"
      },
      "stemmer": {
        "resultat": {
          "prosent": 0.07071,
          "endring": {
            "samme": null
          },
          "antall": {
            "total": 4,
            "fhs": 4
          }
        }
      }
    },
    {
      "id": {
        "partikategori": 2,
        "partikode": "GENP",
        "navn": "Generasjonspartiet"
      },
      "stemmer": {
        "resultat": {
          "prosent": 1.11366,
          "endring": {
            "samme": null
          },
          "antall": {
            "total": 63,
            "fhs": 63
          }
        }
      }
    },
    {
      "id": {
        "partikategori": 2,
        "partikode": "HELSE",
        "navn": "Velferd og Innovasjonspartiet"
      },
      "stemmer": {
        "resultat": {
          "prosent": 0.07071,
          "endring": {
            "samme": null
          },
          "antall": {
            "total": 4,
            "fhs": 4
          }
        }
      }
    },
    {
      "id": {
        "partikategori": 2,
        "partikode": "INP",
        "navn": "Industri- og Næringspartiet"
      },
      "stemmer": {
        "resultat": {
          "prosent": 0.45961,
          "endring": {
            "samme": null
          },
          "antall": {
            "total": 26,
            "fhs": 26
          }
        }
      }
    },
    {
      "id": {
        "partikategori": 2,
        "partikode": "KRISTNE",
        "navn": "Konservativt"
      },
      "stemmer": {
        "resultat": {
          "prosent": 0.28284,
          "endring": {
            "samme": null
          },
          "antall": {
            "total": 16,
            "fhs": 16
          }
        }
      }
    },
    {
      "id": {
        "partikategori": 2,
        "partikode": "PP",
        "navn": "Pensjonistpartiet"
      },
      "stemmer": {
        "resultat": {
          "prosent": 0.95457,
          "endring": {
            "samme": null
          },
          "antall": {
            "total": 54,
            "fhs": 54
          }
        }
      }
    },
    {
      "id": {
        "partikategori": 2,
        "partikode": "PS",
        "navn": "Partiet Sentrum"
      },
      "stemmer": {
        "resultat": {
          "prosent": 0.10606,
          "endring": {
            "samme": null
          },
          "antall": {
            "total": 6,
            "fhs": 6
          }
        }
      }
    },
    {
      "id": {
        "partikategori": 3,
        "partikode": "BLANKE",
        "navn": "Blanke"
      },
      "stemmer": {
        "resultat": {
          "antall": {
            "total": 46,
            "fhs": 46
          }
        }
      }
    },
    {
      "id": {
        "partikategori": 0,
        "partikode": "Andre",
        "navn": "Andre"
      },
      "stemmer": {
        "resultat": {
          "prosent": 3.69454,
          "endring": {
            "samme": null
          },
          "antall": {
            "total": 209,
            "fhs": 209
          }
        }
      }
    },
    {
      "id": {
        "partikategori": 0,
        "partikode": "Andre2",
        "navn": "Andre2"
      },
      "stemmer": {
        "resultat": {
          "prosent": 0.0,
          "endring": {
            "samme": null
          },
          "antall": {
            "total": 0,
            "fhs": 0
          }
        }
      }
    }
  ],
  "_links": {
    "related": [],
    "self": {
      "nr": "4013",
      "href": "/2025/st/12/4601/4013",
      "hrefNavn": "/2025/st/hordaland/bergen/ikea",
      "navn": "IKEA"
    },
    "up": {
      "nr": "4601",
      "href": "/2025/st/12/4601",
      "hrefNavn": "/2025/st/hordaland/bergen",
      "navn": "Bergen"
    }
  }
}